enhancer-0.3.4-py3.10-nspkg.pth
safety/_python/builtin.py
safety/_python/refresher.py
safety/tools/__init__.py
enhancer-0.3.4.dist-info/METADATA
enhancer-0.3.4.dist-info/WHEEL
enhancer-0.3.4.dist-info/namespace_packages.txt
enhancer-0.3.4.dist-info/top_level.txt
enhancer-0.3.4.dist-info/RECORD
