Metadata-Version: 2.1
Name: enhancer
Version: 0.3.4
Summary: Made for me!
Home-page: https://github.com
Author: Infinity
Author-email: Newton@gmail.com
License: UNKNOWN
Platform: UNKNOWN
Classifier: Programming Language :: Python :: 3
Classifier: Programming Language :: Python :: 3.6
Classifier: Programming Language :: Python :: 3.7
Classifier: Programming Language :: Python :: 3.8
Classifier: Programming Language :: Python :: 3.9
Requires-Python: >=3.6
